{
  "pre_hardmode": {
    "king_slime": {
      "name": "Король слизней",
      "stage": "Дохардмод",
      "difficulty": "Лёгкий",
      "threat_profile": "Основная опасность — зажатие в угол и урон от приземления сверху. Угроза возрастает без вертикальной мобильности.",
      "minimum_requirements": "200 HP достаточно, если есть прыжок или верёвки. Без вертикального манёвра босс легко зажимает.",
      "recommended_armor": "Свинцовая или железная броня. Защиты достаточно, так как урон босса невысок.",
      "required_resources": "Гель — для базовых предметов. Металлические слитки — крафт первой брони и оружия.",
      "weapons": {
        "warrior": "Копьё или меч с отбрасыванием. Позволяет держать дистанцию в ближнем бою.",
        "ranger": "Лук с обычными стрелами. Безопасный урон без контакта.",
        "mage": "Посох искр. Простой магический урон без риска.",
        "summoner": "Посох зяблика. Позволяет атаковать, сосредоточившись на уклонении."
      },
      "arena_blueprint": "Ровная площадка с верёвками или 1–2 платформами. Без вертикального пространства босс легко зажимает.",
      "boss_behavior": "Прыгает в сторону игрока, периодически призывает слизней.",
      "damage_windows": "После приземления и во время призыва слизней.",
      "common_failures": "Бой в яме или узком пространстве без возможности прыгать.",
      "recovery_plan": "Добавь верёвки или платформы и увеличь пространство боя.",
      "progression_value": "Даёт стартовые предметы и подготавливает к более подвижным боссам."
    },

    "eye_of_cthulhu": {
      "name": "Глаз Ктулху",
      "stage": "Дохардмод",
      "difficulty": "Средний",
      "threat_profile": "Резкие рывки во второй фазе. Контактный урон быстро наказывает отсутствие скорости.",
      "minimum_requirements": "300 HP, ускорение бега, 12+ защиты. Без скорости босс стабильно догоняет.",
      "recommended_armor": "Золотая или платиновая броня. Снижает контактный урон до переживаемого уровня.",
      "required_resources": "Золото/платина — броня и оружие. Линзы — предмет призыва. Травы — зелья скорости и регенерации.",
      "weapons": {
        "warrior": "Йо-йо или копьё. Постоянный урон без остановки.",
        "ranger": "Лук с огненными стрелами или Минишарк. Полный контроль дистанции.",
        "mage": "Демонский посох. Позволяет держать безопасную дистанцию.",
        "summoner": "Посох зяблика. Требует хорошего движения."
      },
      "arena_blueprint": "2–3 платформы по 120–150 блоков. Короткая арена вынуждает разворачиваться и ловить рывки.",
      "boss_behavior": "Первая фаза умеренная, во второй резко увеличивает скорость и частоту атак.",
      "damage_windows": "После завершения рывка и при призыве слуг.",
      "common_failures": "Маленькая арена, отсутствие зелий, попытка стоять на месте.",
      "recovery_plan": "Удлини арену, добери сердца и возьми дальнобойное оружие.",
      "progression_value": "Открывает путь к Порче или Багрянцу и следующему этапу игры."
    },

    "eater_of_worlds": {
      "name": "Пожиратель миров",
      "stage": "Дохардмод",
      "difficulty": "Средний",
      "threat_profile": "Множественные сегменты наносят урон при контакте. Опасен без проникающего урона.",
      "minimum_requirements": "300 HP и оружие, способное бить сразу несколько сегментов.",
      "recommended_armor": "Золотая/платиновая, позже — демонитовая. Снижает постоянный контактный урон.",
      "required_resources": "Демонит и теневые чешуйки — броня и инструменты. Взрывчатка — контроль сегментов.",
      "weapons": {
        "warrior": "Йо-йо, копья. Хорошо работают по сегментам.",
        "ranger": "Стрелы шута. Пробивают сразу несколько частей.",
        "mage": "Вайл Торн. Идеален против длинных целей.",
        "summoner": "Импы, если доступны. Наносят урон без прямого контакта."
      },
      "arena_blueprint": "Широкие тоннели или отдельная арена. Узкие коридоры резко повышают риск смерти.",
      "boss_behavior": "Делится на сегменты, ускоряется при потере частей.",
      "damage_windows": "Когда сегменты выстраиваются в линию.",
      "common_failures": "Фокус по голове и одиночный урон.",
      "recovery_plan": "Смени оружие на проникающее и расширь пространство боя.",
      "progression_value": "Доступ к демонитовой экипировке и дальнейшему прогрессу."
    },

    "brain_of_cthulhu": {
      "name": "Мозг Ктулху",
      "stage": "Дохардмод",
      "difficulty": "Средний",
      "threat_profile": "Дезориентация из-за иллюзий и телепортаций. Опасен без контроля толпы.",
      "minimum_requirements": "300 HP и стабильный урон по области.",
      "recommended_armor": "Кримтановая броня. Даёт бонусы к выживанию.",
      "required_resources": "Кримтан и образцы ткани — броня и оружие.",
      "weapons": {
        "warrior": "Мечи с широким замахом.",
        "ranger": "Лук с быстрыми стрелами.",
        "mage": "Посохи с АоЕ.",
        "summoner": "Импы или зяблик."
      },
      "arena_blueprint": "Ровная арена с запасом пространства. Ограниченное место усиливает хаос.",
      "boss_behavior": "Сначала иллюзии, затем частые телепорты настоящего мозга.",
      "damage_windows": "После исчезновения иллюзий и сразу после телепорта.",
      "common_failures": "Атака до уничтожения иллюзий.",
      "recovery_plan": "Усиль АоЕ и добавь мобильность.",
      "progression_value": "Кримтановая экипировка и доступ к следующему этапу."
    },

    "queen_bee": {
      "name": "Королева пчёл",
      "stage": "Дохардмод",
      "difficulty": "Средний",
      "threat_profile": "Быстрые рывки и шквал снарядов. Ошибки быстро наказываются.",
      "minimum_requirements": "350 HP и защита от яда. Без этого бой затягивается и становится смертельным.",
      "recommended_armor": "Кримтановая или демонитовая броня. Баланс защиты и урона.",
      "required_resources": "Воск — пчелиные предметы. Джунглевые ресурсы — зелья и оружие.",
      "weapons": {
        "warrior": "Йо-йо, копья — позволяют держать дистанцию.",
        "ranger": "Лук с огненными стрелами. Стабильный урон на расстоянии.",
        "mage": "Водяной болт. Хорош против быстрых целей.",
        "summoner": "Импы. Автоматический урон снижает давление."
      },
      "arena_blueprint": "Широкая арена. Бой в тесном улье резко повышает сложность.",
      "boss_behavior": "Чередует рывки, стрельбу и призыв пчёл.",
      "damage_windows": "После завершения рывка.",
      "common_failures": "Сражение в маленьком улье без арены.",
      "recovery_plan": "Вынеси бой наружу и увеличь пространство.",
      "progression_value": "Пчелиные предметы и мощные зелья."
    },

    "skeletron": {
      "name": "Скелетрон",
      "stage": "Дохардмод",
      "difficulty": "Сложный",
      "threat_profile": "Смертельная голова без уничтожения рук. Высокий урон и скорость.",
      "minimum_requirements": "350–400 HP, высокая мобильность. Без этого бой почти невозможен.",
      "recommended_armor": "Платиновая или кримтановая броня. Максимально снижает урон рук.",
      "required_resources": "Крюк-кошка — мобильность. Зелья скорости и регенерации.",
      "weapons": {
        "warrior": "Йо-йо или копья. Урон по рукам с безопасной дистанции.",
        "ranger": "Минишарк. Быстро уничтожает руки.",
        "mage": "Водяной болт. Позволяет бить из укрытий.",
        "summoner": "Импы. Помогают наносить урон, пока игрок уклоняется."
      },
      "arena_blueprint": "Большая арена у Темницы. Маленькая арена = быстрый вайп.",
      "boss_behavior": "Сначала активны руки, после их уничтожения — агрессивная голова.",
      "damage_windows": "После уничтожения обеих рук.",
      "common_failures": "Игнор рук и попытка пережить бой без мобильности.",
      "recovery_plan": "Увеличь арену и сфокусируй урон на руках.",
      "progression_value": "Открывает полный доступ к Темнице."
    },

    "wall_of_flesh": {
      "name": "Стена плоти",
      "stage": "Переход в Хардмод",
      "difficulty": "Сложный",
      "threat_profile": "Постоянное давление, ускорение и шквал приспешников. Ошибки не прощаются.",
      "minimum_requirements": "400 HP и стабильный дальний урон. Без этого бой не дожить.",
      "recommended_armor": "Кримтановая или демонитовая броня. Баланс защиты и урона.",
      "required_resources": "Адские блоки — длинная дорога. Адское оружие — стабильный DPS.",
      "weapons": {
        "warrior": "Цепы. Позволяют наносить урон, не сближаясь.",
        "ranger": "Лук с адскими стрелами. Постоянный урон на дистанции.",
        "mage": "Водяной болт. Хороший урон при движении.",
        "summoner": "Импы. Постоянный урон без остановки."
      },
      "arena_blueprint": "Длинная ровная дорога через весь Ад. Короткая дорога = смерть.",
      "boss_behavior": "Медленно движется, усиливая давление по мере боя.",
      "damage_windows": "Постоянно, при фокусе на глазах.",
      "common_failures": "Недостаточная длина дороги и слабый DPS.",
      "recovery_plan": "Удлини дорогу и усили дальний урон.",
      "progression_value": "Запускает Хардмод и открывает вторую половину игры."
    }
  }
}